odoo/addons/web_widget_bokeh_chart/README.rst
odoo/addons/web_widget_bokeh_chart/__init__.py
odoo/addons/web_widget_bokeh_chart/__manifest__.py
odoo/addons/web_widget_bokeh_chart/i18n/web_widget_bokeh_chart.pot
odoo/addons/web_widget_bokeh_chart/i18n/zh_CN.po
odoo/addons/web_widget_bokeh_chart/readme/CONTRIBUTORS.rst
odoo/addons/web_widget_bokeh_chart/readme/CREDITS.rst
odoo/addons/web_widget_bokeh_chart/readme/DESCRIPTION.rst
odoo/addons/web_widget_bokeh_chart/readme/INSTALL.rst
odoo/addons/web_widget_bokeh_chart/readme/USAGE.rst
odoo/addons/web_widget_bokeh_chart/static/description/example.png
odoo/addons/web_widget_bokeh_chart/static/description/icon.png
odoo/addons/web_widget_bokeh_chart/static/description/index.html
odoo/addons/web_widget_bokeh_chart/static/src/js/web_widget_bokeh_chart.js
odoo/addons/web_widget_bokeh_chart/static/src/lib/bokeh/bokeh-2.3.1.min.js
odoo/addons/web_widget_bokeh_chart/static/src/lib/bokeh/bokeh-api-2.3.1.min.js
odoo/addons/web_widget_bokeh_chart/static/src/lib/bokeh/bokeh-widgets-2.3.1.min.js
odoo/addons/web_widget_bokeh_chart/views/web_widget_bokeh_chart.xml
odoo14_addon_web_widget_bokeh_chart-14.0.2.3.1.dist-info/METADATA
odoo14_addon_web_widget_bokeh_chart-14.0.2.3.1.dist-info/WHEEL
odoo14_addon_web_widget_bokeh_chart-14.0.2.3.1.dist-info/top_level.txt
odoo14_addon_web_widget_bokeh_chart-14.0.2.3.1.dist-info/RECORD
