Metadata-Version: 2.1
Name: odoo14-addon-web-widget-bokeh-chart
Version: 14.0.2.3.1
Summary: This widget allows to display charts using Bokeh library.
Home-page: https://github.com/OCA/web
Author: ForgeFlow, Odoo Community Association (OCA)
Author-email: support@odoo-community.org
License: LGPL-3
Platform: UNKNOWN
Classifier: Programming Language :: Python
Classifier: Framework :: Odoo
Classifier: License :: OSI Approved :: GNU Lesser General Public License v3 (LGPLv3)
Classifier: Development Status :: 5 - Production/Stable
Requires-Python: >=3.6
Requires-Dist: bokeh (==2.3.1)
Requires-Dist: odoo (<14.1dev,>=14.0a)
